{
  "title": "Dylan Hyde",
  "pageid": 4691,
  "url": "https://bitlife-life-simulator.fandom.com/wiki/Dylan_Hyde",
  "categories": [
    "British_People",
    "Criminals",
    "Engineers",
    "Fan_Characters",
    "Prisoners"
  ],
  "links": [],
  "fetched_at": "2026-06-18T07:04:17.882731+00:00",
  "source": "bitlife-life-simulator.fandom.com/api.php",
  "files": {
    "html": "pages/Dylan_Hyde/content.html",
    "wikitext": "pages/Dylan_Hyde/content.wikitext",
    "text": "pages/Dylan_Hyde/content.txt"
  }
}