{
  "title": "Echo Leventis-Adamantios",
  "pageid": 4921,
  "url": "https://bitlife-life-simulator.fandom.com/wiki/Echo_Leventis-Adamantios",
  "categories": [
    "Fan_Characters"
  ],
  "links": [],
  "fetched_at": "2026-06-18T07:04:17.882731+00:00",
  "source": "bitlife-life-simulator.fandom.com/api.php",
  "files": {
    "html": "pages/Echo_Leventis-Adamantios/content.html",
    "wikitext": "pages/Echo_Leventis-Adamantios/content.wikitext",
    "text": "pages/Echo_Leventis-Adamantios/content.txt"
  }
}