{
  "title": "Licenses",
  "pageid": 3539,
  "url": "https://bitlife-life-simulator.fandom.com/wiki/Licenses",
  "categories": [
    "BitLife"
  ],
  "links": [
    "Assets",
    "Astronaut",
    "Crime",
    "Karma",
    "Murder",
    "Nations",
    "Shopping"
  ],
  "fetched_at": "2026-06-18T07:04:17.882731+00:00",
  "source": "bitlife-life-simulator.fandom.com/api.php",
  "files": {
    "html": "pages/Licenses/content.html",
    "wikitext": "pages/Licenses/content.wikitext",
    "text": "pages/Licenses/content.txt"
  }
}