{
  "title": "Ronald Ali, Sr.",
  "pageid": 5826,
  "url": "https://bitlife-life-simulator.fandom.com/wiki/Ronald_Ali%2C_Sr.",
  "categories": [
    "British_People",
    "Drug_dealers",
    "Fan_Characters",
    "Kings",
    "Royality"
  ],
  "links": [
    "Ronald, Marquess of Cockwallace"
  ],
  "fetched_at": "2026-06-18T07:04:17.882731+00:00",
  "source": "bitlife-life-simulator.fandom.com/api.php",
  "files": {
    "html": "pages/Ronald_Ali__Sr./content.html",
    "wikitext": "pages/Ronald_Ali__Sr./content.wikitext",
    "text": "pages/Ronald_Ali__Sr./content.txt"
  }
}