{
  "title": "Tudor Avram",
  "pageid": 5201,
  "url": "https://bitlife-life-simulator.fandom.com/wiki/Tudor_Avram",
  "categories": [
    "Actors",
    "Characters",
    "Criminals",
    "Doctors",
    "Fan_Characters",
    "Musicians",
    "Romanians",
    "Serial_killers",
    "Vampires"
  ],
  "links": [],
  "fetched_at": "2026-06-18T07:04:17.882731+00:00",
  "source": "bitlife-life-simulator.fandom.com/api.php",
  "files": {
    "html": "pages/Tudor_Avram/content.html",
    "wikitext": "pages/Tudor_Avram/content.wikitext",
    "text": "pages/Tudor_Avram/content.txt"
  }
}